hvspatialpy/__init__.py
hvspatialpy/hvcorr.py
hvspatialpy/hvspatialpygui.py
hvspatialpy/meta.py
hvspatialpy/pltspatial.py
hvspatialpy-1.0.0.dist-info/License
hvspatialpy-1.0.0.dist-info/METADATA
hvspatialpy-1.0.0.dist-info/WHEEL
hvspatialpy-1.0.0.dist-info/top_level.txt
hvspatialpy-1.0.0.dist-info/RECORD
