Metadata-Version: 2.1
Name: hvspatialpy
Version: 1.0.0
Summary: A python package for evaluating the spatial variability of a site utilizing the Horizontal-to-Vertical Spectral Ratio (HVSR)
Home-page: https://github.com/fjornelas/hvspatialpy
Author: Francisco Javier Ornelas
Author-email: jornela1@g.ucla.edu
License: GNU General Public License v3
Project-URL: Bug Reports, https://github.com/fjornelas/hvspatialpy/issues
Project-URL: Source, https://github.com/fjornelas/hvspatialpy/
Project-URL: Docs, https://fjornelas.github.io/hvspatialpy/
Keywords: HVSR,geospatial statistics,spatial variability
Classifier: Development Status :: 5 - Production/Stable
Classifier: Intended Audience :: Developers
Classifier: Intended Audience :: Education
Classifier: Intended Audience :: Science/Research
Classifier: Topic :: Education
Classifier: Topic :: Scientific/Engineering
Classifier: Topic :: Scientific/Engineering :: Physics
Classifier: License :: OSI Approved :: GNU General Public License v3 (GPLv3)
Classifier: Natural Language :: English
Classifier: Programming Language :: Python :: 3.8
Classifier: Programming Language :: Python :: 3.9
Classifier: Topic :: Software Development :: Version Control :: Git
Requires-Python: >=3.8
License-File: License
Requires-Dist: numpy >=1.20
Requires-Dist: pandas <1.5.4
Requires-Dist: matplotlib
Requires-Dist: obspy
Requires-Dist: scipy
Requires-Dist: parzenpy
Requires-Dist: tslearn
Requires-Dist: scikit-learn
Requires-Dist: rasterio
Requires-Dist: ipywidgets
Requires-Dist: IPython
